<?xml version="1.0" encoding="us-ascii"?>
<Catalog>
    <CActorEventMacroRunnable id="HoggerCapNVar3Macro">
        <Do Send="TextureSelectById storm_hero_Hogger_CapN_Var3_diff"/>
        <Do Send="TextureSelectById storm_hero_Hogger_CapN_Var3_spec"/>
        <Do Send="TextureSelectById storm_hero_Hogger_CapN_Var3_emis"/>
    </CActorEventMacroRunnable>
    <CLight id="Storm_Portrait_Hogger_CapN_Var3" parent="default">
        <ToDInfoArray index="0" Id="Storm_Portrait_Hogger_CapN_Var3" OperatorHDR="4" Colorize="1">
            <AmbientColor X="0.407843" Y="0.329412" Z="0.325490"/>
            <Param index="HDRExposure" value="1.650000"/>
            <Param index="HDRBloomThreshold" value="0.900000"/>
            <Param index="HDRWhitePoint" value="1.850000"/>
            <Param index="TerrainSpecularExp" value="73.000000"/>
            <Param index="CreepSpecularExp" value="30.000000"/>
            <Param index="CreepHDRSpecMultiplier" value="3.000000"/>
            <Param index="ColorizationInputHigh" value="0.975000"/>
            <Param index="ColorizationBlend" value="0.000000"/>
            <Param index="ShadowPenumbraSize" value="0.063000"/>
            <DirectionalLight index="Key" ColorMultiplier="2.000000" SpecColorMultiplier="1.500000">
                <Color X="0.984314" Y="0.874510" Z="0.549020"/>
                <SpecularColor X="0.694118" Y="0.674510" Z="0.466667"/>
                <Direction X="-0.778240" Y="0.265996" Z="-0.568849"/>
            </DirectionalLight>
            <DirectionalLight index="Fill" ColorMultiplier="0.800000">
                <Color X="0.101961" Y="0.576471" Z="0.956863"/>
                <Direction X="0.492423" Y="0.775037" Z="0.396026"/>
            </DirectionalLight>
            <DirectionalLight index="Back" ColorMultiplier="4.000000">
                <Color X="0.992157" Y="0.972549" Z="0.815686"/>
                <Direction X="-0.299321" Y="-0.841985" Z="-0.448851"/>
            </DirectionalLight>
            <DirectionalLight index="Shadow">
                <Color X="0.094118" Y="0.062745" Z="0.078431"/>
                <Direction Y="-0.000000" Z="1.000000"/>
            </DirectionalLight>
        </ToDInfoArray>
        <EditorCategories value="LightGroup:PortraitsUnitsOther"/>
    </CLight>
    <CModel id="HoggerCapNVar3Portrait" parent="HoggerCapNPortraitCommon">
        <Lighting value="Storm_Portrait_Hogger_CapN_Var3"/>
    </CModel>
    <CRewardSkin id="HoggerCapNVar3">
        <License value="92025"/>
    </CRewardSkin>
    <CSkin id="HoggerCapNVar3" parent="HoggerCapNCommon">
        <AttributeId value="HoC4"/>
        <ModelMacroRun Models="HoggerCapNModels" Macro="HoggerCapNVar3Macro"/>
        <ProductId value="137740"/>
        <ReplacementArray Catalog="Model" From="HoggerCapNPortrait" To="HoggerCapNVar3Portrait"/>
        <RequiredRewardArray value="HoggerCapNVar3"/>
        <ReleaseDate Month="12" Day="1" Year="2020"/>
        <HyperlinkId value="DrownedShipwreckerHogger"/>
    </CSkin>
    <CTexture id="storm_hero_Hogger_CapN_Var3_diff" parent="MainSlotTexture"/>
    <CTexture id="storm_hero_Hogger_CapN_Var3_spec" parent="MainSlotTexture"/>
    <CTexture id="storm_hero_Hogger_CapN_Var3_emis" parent="MainSlotTexture"/>
</Catalog>
