<?xml version="1.0" encoding="us-ascii"?>
<Catalog>
    <CRewardSpray id="Classic21Novaspray" parent="StormSpray">
        <License value="266350"/>
    </CRewardSpray>
    <CSpray id="Classic21Novaspray" parent="SprayStaticFluidCommon">
        <AttributeId value="SY9E"/>
        <ProductId value="458222"/>
        <Texture value="Assets/Textures/classic21_nova_spray.dds"/>
        <CollectionCategory value="Default"/>
        <ReleaseDate Month="11" Day="9" Year="2021"/>
    </CSpray>
</Catalog>
