<?xml version="1.0" encoding="us-ascii"?>
<Catalog>
    <CRewardSpray id="SprayAnimatedMobster19DiceSnakeEyes" parent="StormSpray">
        <License value="49675"/>
    </CRewardSpray>
    <CSpray id="SprayAnimatedMobster19DiceSnakeEyes" parent="SprayAnimated2FrameFluidCommon">
        <AttributeId value="SY5p"/>
        <ProductId value="66705"/>
        <Texture value="Assets/Textures/storm_lootspray_animated_mobster19_dicesnakeeyes.dds"/>
        <CollectionCategory value="SeasonalEvents"/>
        <ReleaseDate Month="9" Day="24" Year="2019"/>
        <EventName value="HallowsEnd"/>
        <SortName value="Spray/SortName/SprayAnimatedMobster19"/>
        <HyperlinkId value="SnakeEyes"/>
    </CSpray>
</Catalog>
