<?xml version="1.0" encoding="us-ascii"?>
<Catalog>
    <CRewardSpray id="SprayAnimatedCraft20Shalamayne" parent="StormSpray">
        <License value="57165"/>
        <Spray value="SprayAnimatedCraft20Shalamayne"/>
    </CRewardSpray>
    <CSpray id="SprayAnimatedCraft20Shalamayne" parent="SprayAnimated2FrameFluidCommon">
        <Texture value="Assets/Textures/storm_lootspray_animated_craft20_shalamayne.dds"/>
        <AttributeId value="SY8V"/>
        <ProductId value="79266"/>
        <CollectionCategory value="SeasonalEvents"/>
        <ReleaseDate Month="9" Day="8" Year="2020"/>
        <HyperlinkId value="Shalamayne"/>
        <EventName value="HallowsEnd"/>
    </CSpray>
</Catalog>
