<?xml version="1.0" encoding="us-ascii"?>
<Catalog>
    <CRewardSpray id="SprayStaticMobster19HammerCar" parent="StormSpray">
        <License value="49742"/>
    </CRewardSpray>
    <CSpray id="SprayStaticMobster19HammerCar" parent="SprayStaticFluidCommon">
        <AttributeId value="SY5n"/>
        <ProductId value="66702"/>
        <Texture value="Assets/Textures/storm_lootspray_static_mobster19_hammercar.dds"/>
        <CollectionCategory value="SeasonalEvents"/>
        <ReleaseDate Month="9" Day="24" Year="2019"/>
        <EventName value="HallowsEnd"/>
        <SortName value="Spray/SortName/SprayStaticMobster19"/>
        <HyperlinkId value="CartoonHitmobile"/>
    </CSpray>
</Catalog>
