<?xml version="1.0" encoding="us-ascii"?>
<Catalog>
    <CActorEventMacroRunnable id="MeiOWVar4Macro">
        <Do Send="TextureSelectById Storm_Hero_MeiOW_Base_Var4_Diff"/>
        <Do Send="TextureSelectById Storm_Hero_MeiOW_Base_Var4_Spec"/>
    </CActorEventMacroRunnable>
    <CLight id="Storm_Portrait_MeiOW_Var4" parent="default">
        <ToDInfoArray index="0">
            <Id value="Storm_Portrait_MeiOW_Var4"/>
            <AmbientEnvironmentMultiplier value="0.000000"/>
            <OperatorHDR value="3"/>
            <UseSeparateDetailSSAO value="0"/>
            <AmbientColor X="0.388235" Y="0.352941" Z="0.439216"/>
            <Param index="HDRExposure" value="1.650000"/>
            <Param index="HDRBloomThreshold" value="1.500000"/>
            <Param index="ColorizationBlend" value="0.000000"/>
            <Param index="AOOcclusionRadius" value="8.000000"/>
            <Param index="AONoOcclusion" value="1.000000"/>
            <Param index="AOFullOcclusion" value="1.000000"/>
            <Param index="AOOcclusionPower" value="2.000000"/>
            <Param index="AODetailOcclusionRadius" value="0.200000"/>
            <Param index="AODetailNoOcclusion" value="0.030000"/>
            <Param index="AODetailFullOcclusion" value="0.030000"/>
            <Param index="AODetailOcclusionPower" value="1.000000"/>
            <Param index="ShadowPenumbraSize" value="0.171000"/>
            <DirectionalLight index="Key" ColorMultiplier="0.841000" SpecColorMultiplier="1.500000">
                <Color X="0.545098" Y="0.749020" Z="0.980392"/>
                <SpecularColor X="0.858824" Y="0.886275" Z="0.929412"/>
                <Direction X="0.327159" Y="0.789052" Z="-0.519966"/>
            </DirectionalLight>
            <DirectionalLight index="Fill">
                <Color X="0.654902" Y="0.101961" Z="0.349020"/>
                <Direction X="-0.848508" Y="0.437385" Z="-0.297874"/>
            </DirectionalLight>
            <DirectionalLight index="Back" ColorMultiplier="5.000000">
                <Color X="0.600000" Y="0.819608" Z="0.984314"/>
                <Direction X="-0.042703" Y="-0.966457" Z="-0.253252"/>
            </DirectionalLight>
            <DirectionalLight index="Shadow">
                <Direction Z="1.000000"/>
            </DirectionalLight>
            <Variations Command="MoreRed" Sensitivity="1"/>
            <Variations Command="MoreYellow" Sensitivity="1"/>
        </ToDInfoArray>
        <EditorCategories value="LightGroup:PortraitsUnitsOther"/>
    </CLight>
    <CModel id="MeiOWPortraitVar4" parent="MeiOWPortraitCommon">
        <Lighting value="Storm_Portrait_MeiOW_Var4"/>
    </CModel>
    <CRewardSkin id="MeiOWVar4">
        <License value="53378"/>
    </CRewardSkin>
    <CSkin id="MeiOWVar4" parent="MeiOWBaseCommon">
        <AttributeId value="Mei3"/>
        <ProductId value="74401"/>
        <ModelMacroRun Models="MeiOWBaseModels" Macro="MeiOWVar4Macro"/>
        <ModelMacroRun Models="MeiOWBlizzardLoopFXModels" Macro="MeiOWVar4Macro"/>
        <Name value="Skin/Name/MeiOWVar4"/>
        <ReplacementArray Catalog="Model" From="MeiOWPortrait" To="MeiOWPortraitVar4"/>
        <RequiredRewardArray value="MeiOWVar4"/>
        <SortName value="Skin/SortName/MeiOWBaseCommonVar0"/>
        <AdditionalSearchText value="Skin/AdditionalSearchText/MeiOWVar4"/>
        <Rarity value="Rare"/>
        <HyperlinkId value="RenownedMei"/>
    </CSkin>
    <CTexture id="Storm_Hero_MeiOW_Base_Var4_Diff" parent="MainSlotTexture"/>
    <CTexture id="Storm_Hero_MeiOW_Base_Var4_Spec" parent="MainSlotTexture"/>
</Catalog>
