<?xml version="1.0" encoding="us-ascii"?>
<Catalog>
  <CActorEventMacroRunnable id="DehakaToys18Var3Macro">
    <Do Send="ModelMaterialApply DehakaToys18Var3Material" />
  </CActorEventMacroRunnable>
  <CActorEventMacroRunnable id="DehakaToys18Var3DeathMacro">
    <Do Send="ModelMaterialApply DehakaToys18Var3DeathMaterial" />
  </CActorEventMacroRunnable>
  <CActorModelMaterial id="DehakaToys18Var3Material">
    <MaterialType value="Replacement" />
  </CActorModelMaterial>
  <CActorModelMaterial id="DehakaToys18Var3DeathMaterial" parent="StormHeroDeathRagdollReplacementMaterial" />
  <CLight id="Storm_Portrait_Dehaka_Toys18_Var3" parent="default">
    <ToDInfoArray index="0" Id="Storm_Portrait_Dehaka_Toys18_Var3" OperatorHDR="4" Colorize="1">
      <AmbientColor X="0.392157" Y="0.352941" Z="0.313726" />
      <Param index="HDRExposure" value="1.650000" />
      <Param index="HDREmisMultiplier" value="1.600000" />
      <Param index="ColorizationInputHigh" value="0.975000" />
      <Param index="ColorizationHue" value="0.001000" />
      <Param index="ColorizationBlend" value="0.000000" />
      <DirectionalLight index="Key" ColorMultiplier="1.300000" SpecColorMultiplier="4.000000">
        <Color X="0.603922" Y="0.721569" Z="0.741176" />
        <SpecularColor X="0.764706" Y="0.764706" Z="0.839216" />
        <Direction X="0.151115" Y="0.765994" Z="-0.624834" />
      </DirectionalLight>
      <DirectionalLight index="Fill" ColorMultiplier="0.600000">
        <Color X="0.607843" Y="0.741176" Z="0.423529" />
        <Direction X="-0.284186" Y="0.935955" Z="0.207912" />
      </DirectionalLight>
      <DirectionalLight index="Back" ColorMultiplier="4.000000">
        <Color X="0.058824" Y="0.811765" Z="0.874510" />
        <Direction X="-0.906308" Y="-0.422618" Z="0.000000" />
      </DirectionalLight>
      <DirectionalLight index="Shadow">
        <Direction Z="1.000000" />
      </DirectionalLight>
    </ToDInfoArray>
    <EditorCategories value="LightGroup:PortraitsUnitsOther" />
  </CLight>
  <CModel id="DehakaToys18Var3Material">
    <Model value="Assets\Effects\Glaze\Storm_Hero_Dehaka_Toys18_Var3_Mat\Storm_Hero_Dehaka_Toys18_Var3_Mat.m3" />
  </CModel>
  <CModel id="DehakaToys18Var3DeathMaterial" parent="HeroDeathRagdoll">
    <Model value="Assets\Effects\Glaze\Storm_Hero_Dehaka_Toys18_Var3_Death_Mat\Storm_Hero_Dehaka_Toys18_Var3_Death_Mat.m3" />
  </CModel>
  <CModel id="DehakaToys18Var3Portrait" parent="DehakaSkinToys18Portrait">
    <Lighting value="Storm_Portrait_Dehaka_Toys18_Var3" />
  </CModel>
  <CRewardSkin id="DehakaToys18Var3">
    <License value="51311" />
  </CRewardSkin>
  <CSkin id="DehakaToys18Var3" parent="DehakaToys18Common">
    <ReplacementArray Catalog="Model" From="DehakaSkinToys18Portrait" To="DehakaToys18Var3Portrait" />
    <ReplacementArray Catalog="VoiceOver" From="DehakaBase" To="DehakaToys18" />
    <AttributeId value="Deh6" />
    <ProductId value="71467" />
    <RequiredRewardArray value="DehakaToys18Var3" />
    <ModelMacroRun Models="DehakaSkinToys18MatSwapModels" Macro="DehakaToys18Var3Macro" />
    <ModelMacroRun Models="DehakaSkinToys18MatSwapDeathModels" Macro="DehakaToys18Var3DeathMacro" />
    <PreviewCutsceneFile value="Cutscenes\StoreDehakaToys18Var3.StormCutscene" />
    <ReleaseDate Month="12" Day="17" Year="2019" />
    <HyperlinkId value="FerociousDehakasaurusRex" />
  </CSkin>
</Catalog>